- [[#red]]==两个String对象用"+"拼接会被优化为StringBuffer的append拼接，然后toString方法，与new一样会直接在堆中创建对象。==
- ## 例子1：字面量对象和new的对象对比
	- ```java
	  String a = "hello"
	  String b = "hello"
	  String c = new String("hello")  
	  ```
	- 问：a == b == c?，为什么？[[#red]]==**字面量对象存在字符串常量池中。堆中对象存在堆中**==
		- 1、ab都是隐式创建字符串对象的【非new】
		- 2、首先java程序执行第一个“hello”字面量时，根据字面量去 字符串常量池中查找是否存在相同的字面量对象，
		  collapsed:: true
			- 存在即返回该对象的引用，
			- 不存在则在字符串常量池中中创建字符串对象，并按字面量保存对象引用，所以a会有个新建的对象，加入到字符串常量池中，a的值为该对象的引用0x01
		- 3、执行到b也会去字符串常量池中查找，是否有字面量“hello”相等的对象，之前a已经创建过了，则也会把0x01对象引用赋值给b   那么  a == b
		- 4、而通过`new`关键字显式创建的字符串对象，无论字符串常量池中是否存在相同值的字符串对象，都会在堆内存中创建一个新的字符串对象。c = 0x02
		- 所以a ==b != c
		-
- ## 例子2、字面量+拼接 和 对象+拼接的对比
	- ```java
	  5个对象 字符串常量池 a\b   堆 a\b\ab 
	  String s3 = new String("a") + new String("b");// s3引用的是堆对象
	  
	  被优化成  “ab”  对应字面量对象
	  String s4 = "a" + "b"; // 对应的字面量对象
	  s3 == s4吗 // false
	  ```
	- > [[#red]]==两个String对象用"+"拼接会被优化为StringBuffer的append拼接，然后toString方法，与new一样会直接在堆中创建对象。==
	-
	- >"a"和"b"都是字符串字面量，在编译时会直接将它们拼接为一个新的字符串字面量"ab"。由于这个拼接操作是在编译时进行的，编译器会对字符串字面量进行优化，使得`s4`直接指向字符串常量池中的同一个对象。
	-
- ## 例子3：多种混合
	- 代码：
		- ```java
		  String s1 = "Hello";
		  String s2 = "Hello";
		  String s3 = "Hel" + "lo";
		  String s4 = "Hel" + new String("lo");
		  String s5 = new String("Hello");
		  String s7 = "H";
		  String s8 = "ello";
		  String s9 = s7 + s8;
		  
		  System.out.println(s1 == s2);  // true
		  System.out.println(s1 == s3);  // true
		  System.out.println(s1 == s4);  // false
		  System.out.println(s1 == s9);  // false
		  ```
	- ### 1) s1 == s2  true
	  collapsed:: true
		- 这个对比第一部分常量池的讲解应该很好理解，因为字面量`"Hello"`在运行时会进入运行时常量池(中的字符串常量池，JDK1.7以前)，同时同一份字面量只会保留一份，所有引用都指向这一份字符串，自然引用的地址也就相同了。
	- ### 2) s1 == s3 true
		- 这个主要牵扯String"+"号编译器优化的问题，s3虽然是动态拼接出来的字符串，但是所有参与拼接的部分都是已知的字面量，在编译期间，这种拼接会被优化，编译器直接帮你拼好，因此String s3 = "Hel" + "lo";在class文件中被优化成String s3 = "Hello";，所以s1 == s3成立。
		- 验证查看编译结果
		  collapsed:: true
			- ```JAVA
			  public static void main(java.lang.String[]);
			      descriptor: ([Ljava/lang/String;)V
			      flags: ACC_PUBLIC, ACC_STATIC
			      Code:
			        stack=3, locals=3, args_size=1
			           0: ldc           #2                  // String Hello
			           2: astore_1
			           3: ldc           #2                  // String Hello
			           5: astore_2
			           6: getstatic     #3                  // Field java/lang/System.out:Ljava/io/PrintStream;
			           9: aload_1
			          10: aload_2
			          11: if_acmpne     18
			          14: iconst_1
			          15: goto          19
			          18: iconst_0
			          19: invokevirtual #4                  // Method java/io/PrintStream.println:(Z)V
			          22: return
			  ```
		- 通过查看编译后的方法代码，可以看到这里加入操作数栈的ldc指令有两次，都是“Hello”，没有出现“Hel”或者“lo”,同时这两个“Hello”指向常量池的通过一个地址，都是`#2`，因此常量池中也只存在一个`“Hello”`字面量。
	- ### 3) s1 == s4 false
	  collapsed:: true
		- 因为s1是字面量创建的对象，存入字符串常量池中，s4涉及对象的拼接而不是单纯的字面量拼接，会和new一样直接在堆中创建对象。
		- 其实这个也不难理解，但是我们还是先来看看编译后的字节码：
		  collapsed:: true
			- ```java
			  public static void main(java.lang.String[]);
			      descriptor: ([Ljava/lang/String;)V
			      flags: ACC_PUBLIC, ACC_STATIC
			      Code:
			        stack=4, locals=3, args_size=1
			           0: ldc           #2                  // String Hello
			           2: astore_1
			           3: new           #3                  // class java/lang/StringBuilder
			           6: dup
			           7: invokespecial #4                  // Method java/lang/StringBuilder."<init>":()V
			          10: ldc           #5                  // String Hel
			          12: invokevirtual #6                  // Method java/lang/StringBuilder.append:(Ljava/lang/String;)Ljava/lang/StringBuilder;
			          15: new           #7                  // class java/lang/String
			          18: dup
			          19: ldc           #8                  // String lo
			          21: invokespecial #9                  // Method java/lang/String."<init>":(Ljava/lang/String;)V
			          24: invokevirtual #6                  // Method java/lang/StringBuilder.append:(Ljava/lang/String;)Ljava/lang/StringBuilder;
			          27: invokevirtual #10                 // Method java/lang/StringBuilder.toString:()Ljava/lang/String;
			          30: astore_2
			          31: getstatic     #11                 // Field java/lang/System.out:Ljava/io/PrintStream;
			          34: aload_1
			          35: aload_2
			          36: if_acmpne     43
			          39: iconst_1
			          40: goto          44
			          43: iconst_0
			          44: invokevirtual #12                 // Method java/io/PrintStream.println:(Z)V
			          47: return
			  ```
		- 我们就不对操作符一一解释了，可以看到这次确实出现了`“String Hel”`和`“String lo”`，原因上面我们也说过，这是因为`new String("lo")`在堆中new了一个String对象出来，而`“Hel”`字面量是通过另一种操作在堆中创建的对象，这两个在堆中不同地方创建的对象是通过`StringBuilder.append`方法拼接出来的，并且最终会调用`StringBuilder.toString`方法输出(最终输出的也是“Hello”),这些通过上面字节码的分析都可以看得出来，我们来看看`StringBuilder.toString`方法：
		  collapsed:: true
			- ```java
			  @Override
			      public String toString() {
			          // Create a copy, don't share the array
			          return new String(value, 0, count);
			      }
			  ```
		- 可以看到，这个最终是拼接出来的一个String对象，也就是说，s4指向的一个经过StringBuilder拼接之后的String对象，而s1指向的是另一个对象，这两个对象的地址当然是不同的了。
	- ### 4) s1 == s9 false
		- 字节码：
		  collapsed:: true
			- ```java
			  public static void main(java.lang.String[]);
			      descriptor: ([Ljava/lang/String;)V
			      flags: ACC_PUBLIC, ACC_STATIC
			      Code:
			        stack=3, locals=5, args_size=1
			           0: ldc           #2                  // String Hello
			           2: astore_1
			           3: ldc           #3                  // String H
			           5: astore_2
			           6: ldc           #4                  // String ello
			           8: astore_3
			           9: new           #5                  // class java/lang/StringBuilder
			          12: dup
			          13: invokespecial #6                  // Method java/lang/StringBuilder."<init>":()V
			          16: aload_2
			          17: invokevirtual #7                  // Method java/lang/StringBuilder.append:(Ljava/lang/String;)Ljava/lang/StringBuilder;
			          20: aload_3
			          21: invokevirtual #7                  // Method java/lang/StringBuilder.append:(Ljava/lang/String;)Ljava/lang/StringBuilder;
			          24: invokevirtual #8                  // Method java/lang/StringBuilder.toString:()Ljava/lang/String;
			          27: astore        4
			          29: getstatic     #9                  // Field java/lang/System.out:Ljava/io/PrintStream;
			          32: aload_1
			          33: aload         4
			          35: if_acmpne     42
			          38: iconst_1
			          39: goto          43
			          42: iconst_0
			          43: invokevirtual #10                 // Method java/io/PrintStream.println:(Z)V
			          46: return
			  ```
		- s1 是字面量通过字符串常量池创建的对象，s7、s8也会根据字面量去常量池查找，没有创建对象，所以s9和s4类似都是对象拼接，创建新的对象。
	-
- # 1、[[String的创建方式和分配内存地址]]
- # 2、StringBuffer和StringBuilder区别
	- StringBuffer是线程同步的。通常用于多线程。
	- StringBuilder是线程不同步的。通常用于单线程。 它的出现提高效率。